area_calculator_dci1234/__init__.py
area_calculator_dci1234/circle_area.py
area_calculator_dci1234/square.py
area_calculator_dci1234/welcome.py
area_calculator_dci1234-0.0.4.dist-info/LICENSE
area_calculator_dci1234-0.0.4.dist-info/METADATA
area_calculator_dci1234-0.0.4.dist-info/WHEEL
area_calculator_dci1234-0.0.4.dist-info/top_level.txt
area_calculator_dci1234-0.0.4.dist-info/RECORD
