Metadata-Version: 2.1
Name: area_calculator_dci1234
Version: 0.0.4
Summary: Calculate areas of geometrical figures
Home-page: UNKNOWN
Author: Maksym Kharchenko
License: UNKNOWN
Keywords: python,calculator,math
Platform: UNKNOWN
Classifier: Development Status :: 1 - Planning
Classifier: Intended Audience :: Education
Classifier: License :: OSI Approved :: GNU General Public License v3 (GPLv3)
Classifier: Programming Language :: Python :: 3
Classifier: Operating System :: POSIX :: Linux
Classifier: Operating System :: MacOS :: MacOS X
Classifier: Operating System :: Microsoft :: Windows
License-File: LICENSE
